tango/__init__.py
tango/__main__.py
tango/cli.py
tango/executor.py
tango/format.py
tango/py.typed
tango/settings.py
tango/step.py
tango/step_cache.py
tango/step_graph.py
tango/step_info.py
tango/version.py
tango/workspace.py
tango/common/__init__.py
tango/common/aliases.py
tango/common/dataset_dict.py
tango/common/det_hash.py
tango/common/exceptions.py
tango/common/file_lock.py
tango/common/from_params.py
tango/common/lazy.py
tango/common/logging.py
tango/common/params.py
tango/common/registrable.py
tango/common/remote_utils.py
tango/common/sequences.py
tango/common/tqdm.py
tango/common/util.py
tango/common/testing/__init__.py
tango/common/testing/steps.py
tango/executors/__init__.py
tango/executors/multicore_executor.py
tango/integrations/__init__.py
tango/integrations/beaker/__init__.py
tango/integrations/beaker/common.py
tango/integrations/beaker/entrypoint.sh
tango/integrations/beaker/executor.py
tango/integrations/beaker/step_cache.py
tango/integrations/beaker/workspace.py
tango/integrations/datasets/__init__.py
tango/integrations/fairscale/__init__.py
tango/integrations/fairscale/fsdp_config.py
tango/integrations/fairscale/module_wrapper.py
tango/integrations/fairscale/training_engine.py
tango/integrations/flax/__init__.py
tango/integrations/flax/data.py
tango/integrations/flax/eval.py
tango/integrations/flax/eval_callback.py
tango/integrations/flax/format.py
tango/integrations/flax/model.py
tango/integrations/flax/optim.py
tango/integrations/flax/train.py
tango/integrations/flax/train_callback.py
tango/integrations/flax/train_config.py
tango/integrations/flax/util.py
tango/integrations/flax/wrapper.py
tango/integrations/gs/__init__.py
tango/integrations/gs/common.py
tango/integrations/gs/step_cache.py
tango/integrations/gs/workspace.py
tango/integrations/torch/__init__.py
tango/integrations/torch/data.py
tango/integrations/torch/eval.py
tango/integrations/torch/eval_callback.py
tango/integrations/torch/exceptions.py
tango/integrations/torch/format.py
ai2_tango-1.3.2.dist-info/LICENSE
ai2_tango-1.3.2.dist-info/METADATA
ai2_tango-1.3.2.dist-info/WHEEL
ai2_tango-1.3.2.dist-info/entry_points.txt
ai2_tango-1.3.2.dist-info/top_level.txt
ai2_tango-1.3.2.dist-info/RECORD
