Metadata-Version: 2.1
Name: ai2-tango
Version: 1.3.2
Summary: A library for choreographing your machine learning research.
Author-email: Allen Institute for Artificial Intelligence <contact@allenai.org>
License: Apache License
Project-URL: homepage, https://github.com/allenai/tango
Project-URL: repository, https://github.com/allenai/tango
Classifier: Intended Audience :: Science/Research
Classifier: Development Status :: 3 - Alpha
Classifier: License :: OSI Approved :: Apache Software License
Classifier: Programming Language :: Python :: 3
Classifier: Topic :: Scientific/Engineering :: Artificial Intelligence
Requires-Python: >=3.8.1
License-File: LICENSE
Requires-Dist: cached-path <2.0,>=1.0
Requires-Dist: rjsonnet >=0.5.0
Requires-Dist: GitPython <4.0,>=3.0
Requires-Dist: PyYAML <7.0,>=5.4.1
Requires-Dist: dill
Requires-Dist: base58
Requires-Dist: xxhash
Requires-Dist: filelock <4.0,>=3.4
Requires-Dist: click <8.1.4,>=8.0
Requires-Dist: click-help-colors <0.10,>=0.9.1
Requires-Dist: rich <14.0,>=12.3
Requires-Dist: tqdm <5.0,>=4.62
Requires-Dist: more-itertools <10.0,>=8.0
Requires-Dist: sqlitedict
Requires-Dist: glob2 >=0.7
Requires-Dist: petname <3.0,>=2.6
Requires-Dist: pytz
Provides-Extra: all
Requires-Dist: ai2-tango[beaker,datasets,examples,fairscale,flax,gs,torch,transformers,wandb] ; extra == 'all'
Provides-Extra: beaker
Requires-Dist: beaker-py <2.0,>=1.14.0 ; extra == 'beaker'
Provides-Extra: datasets
Requires-Dist: datasets <3.0,>=1.12 ; extra == 'datasets'
Provides-Extra: dev
Requires-Dist: ruff ; extra == 'dev'
Requires-Dist: mypy ==1.2.0 ; extra == 'dev'
Requires-Dist: types-PyYAML ; extra == 'dev'
Requires-Dist: types-setuptools ; extra == 'dev'
Requires-Dist: types-pytz ; extra == 'dev'
Requires-Dist: types-retry ; extra == 'dev'
Requires-Dist: black ==23.3.0 ; extra == 'dev'
Requires-Dist: isort ==5.12.0 ; extra == 'dev'
Requires-Dist: pytest ; extra == 'dev'
Requires-Dist: pytest-sphinx ; extra == 'dev'
Requires-Dist: flaky ; extra == 'dev'
Requires-Dist: twine >=1.11.0 ; extra == 'dev'
Requires-Dist: setuptools ; extra == 'dev'
Requires-Dist: wheel ; extra == 'dev'
Requires-Dist: build ; extra == 'dev'
Requires-Dist: Sphinx ==5.3.0 ; extra == 'dev'
Requires-Dist: furo ==2023.3.27 ; extra == 'dev'
Requires-Dist: myst-parser ==1.0.0 ; extra == 'dev'
Requires-Dist: sphinx-copybutton ==0.5.2 ; extra == 'dev'
Requires-Dist: sphinx-autobuild ==2021.3.14 ; extra == 'dev'
Requires-Dist: sphinx-autodoc-typehints <=1.23.0 ; extra == 'dev'
Requires-Dist: packaging ; extra == 'dev'
Provides-Extra: examples
Requires-Dist: torchmetrics >=0.7.0 ; extra == 'examples'
Provides-Extra: fairscale
Requires-Dist: torch <2.1,>=1.9 ; extra == 'fairscale'
Requires-Dist: numpy ; extra == 'fairscale'
Requires-Dist: fairscale <0.5,>=0.4.6 ; extra == 'fairscale'
Provides-Extra: flax
Requires-Dist: datasets <3.0,>=1.12 ; extra == 'flax'
Requires-Dist: jax <=0.4.13,>=0.4.1 ; extra == 'flax'
Requires-Dist: jaxlib <=0.4.13,>=0.4.1 ; extra == 'flax'
Requires-Dist: flax <=0.7.0,>=0.6.1 ; extra == 'flax'
Requires-Dist: optax >=0.1.2 ; extra == 'flax'
Requires-Dist: tensorflow-cpu >=2.9.1 ; extra == 'flax'
Provides-Extra: gs
Requires-Dist: google-cloud-storage >=2.6.0 ; extra == 'gs'
Requires-Dist: google-cloud-datastore >=2.12.0 ; extra == 'gs'
Provides-Extra: torch
Requires-Dist: torch <2.1,>=1.9 ; extra == 'torch'
Requires-Dist: numpy ; extra == 'torch'
Provides-Extra: transformers
Requires-Dist: torch <2.1,>=1.9 ; extra == 'transformers'
Requires-Dist: numpy ; extra == 'transformers'
Requires-Dist: datasets <3.0,>=1.12 ; extra == 'transformers'
Requires-Dist: transformers >=4.12.3 ; extra == 'transformers'
Requires-Dist: sentencepiece ==0.1.98 ; extra == 'transformers'
Requires-Dist: sacremoses ; extra == 'transformers'
Provides-Extra: wandb
Requires-Dist: wandb <0.14.3,>=0.12 ; extra == 'wandb'
Requires-Dist: retry ; extra == 'wandb'
